<?xml version="1.0" encoding="utf-8" ?><dwsync><file name="_languages.js" server="ftp.collegeplacementservices.org" local="3425390845" remote="12018298352" /><file name="_translationstatus.txt" server="ftp.collegeplacementservices.org" local="3425390845" remote="12018298352" /><file name="af.js" server="ftp.collegeplacementservices.org" local="3425390845" remote="12018298352" /><file name="ar.js" server="ftp.collegeplacementservices.org" local="3425390845" remote="12018298352" /><file name="bg.js" server="ftp.collegeplacementservices.org" local="3425390845" remote="12018298352" /><file name="bn.js" server="ftp.collegeplacementservices.org" local="3425390845" remote="12018298352" /><file name="bs.js" server="ftp.collegeplacementservices.org" local="3425390845" remote="12018298352" /><file name="ca.js" server="ftp.collegeplacementservices.org" local="3425390845" remote="12018298352" /><file name="cs.js" server="ftp.collegeplacementservices.org" local="3425390845" remote="12018298352" /><file name="cy.js" server="ftp.collegeplacementservices.org" local="3425390845" remote="12018298352" /><file name="da.js" server="ftp.collegeplacementservices.org" local="3425390845" remote="12018298352" /><file name="de.js" server="ftp.collegeplacementservices.org" local="3425390845" remote="12018298352" /><file name="el.js" server="ftp.collegeplacementservices.org" local="3425390845" remote="12018298352" /><file name="en-au.js" server="ftp.collegeplacementservices.org" local="3425390845" remote="12018298352" /><file name="en-ca.js" server="ftp.collegeplacementservices.org" local="3425390845" remote="12018298352" /><file name="en-gb.js" server="ftp.collegeplacementservices.org" local="3425390845" remote="12018298352" /><file name="en.js" server="ftp.collegeplacementservices.org" local="3425390845" remote="12018298352" /><file name="eo.js" server="ftp.collegeplacementservices.org" local="3425390845" remote="12018298352" /><file name="es.js" server="ftp.collegeplacementservices.org" local="3425390845" remote="12018298352" /><file name="et.js" server="ftp.collegeplacementservices.org" local="3425390845" remote="12018298352" /><file name="eu.js" server="ftp.collegeplacementservices.org" local="3425390845" remote="12018298352" /><file name="fa.js" server="ftp.collegeplacementservices.org" local="3425390845" remote="12018298352" /><file name="fi.js" server="ftp.collegeplacementservices.org" local="3425390845" remote="12018298352" /><file name="fo.js" server="ftp.collegeplacementservices.org" local="3425390845" remote="12018298412" /><file name="fr-ca.js" server="ftp.collegeplacementservices.org" local="3425390845" remote="12018298412" /><file name="fr.js" server="ftp.collegeplacementservices.org" local="3425390845" remote="12018298412" /><file name="gl.js" server="ftp.collegeplacementservices.org" local="3425390845" remote="12018298412" /><file name="gu.js" server="ftp.collegeplacementservices.org" local="3425390845" remote="12018298412" /><file name="he.js" server="ftp.collegeplacementservices.org" local="3425390845" remote="12018298412" /><file name="hi.js" server="ftp.collegeplacementservices.org" local="3425390845" remote="12018298412" /><file name="hr.js" server="ftp.collegeplacementservices.org" local="3425390845" remote="12018298412" /><file name="hu.js" server="ftp.collegeplacementservices.org" local="3425390845" remote="12018298412" /><file name="id.js" server="ftp.collegeplacementservices.org" local="3425390845" remote="12018298412" /><file name="is.js" server="ftp.collegeplacementservices.org" local="3425390845" remote="12018298412" /><file name="it.js" server="ftp.collegeplacementservices.org" local="3425390845" remote="12018298412" /><file name="ja.js" server="ftp.collegeplacementservices.org" local="3425390845" remote="12018298412" /><file name="ka.js" server="ftp.collegeplacementservices.org" local="3425390845" remote="12018298412" /><file name="km.js" server="ftp.collegeplacementservices.org" local="3425390845" remote="12018298412" /><file name="ko.js" server="ftp.collegeplacementservices.org" local="3425390845" remote="12018298412" /><file name="lt.js" server="ftp.collegeplacementservices.org" local="3425390845" remote="12018298412" /><file name="lv.js" server="ftp.collegeplacementservices.org" local="3425390845" remote="12018298412" /><file name="mk.js" server="ftp.collegeplacementservices.org" local="3425390845" remote="12018298412" /><file name="mn.js" server="ftp.collegeplacementservices.org" local="3425390845" remote="12018298412" /><file name="ms.js" server="ftp.collegeplacementservices.org" local="3425390845" remote="12018298412" /><file name="nb.js" server="ftp.collegeplacementservices.org" local="3425390845" remote="12018298412" /><file name="nl.js" server="ftp.collegeplacementservices.org" local="3425390845" remote="12018298412" /><file name="no.js" server="ftp.collegeplacementservices.org" local="3425390845" remote="12018298412" /><file name="pl.js" server="ftp.collegeplacementservices.org" local="3425390845" remote="12018298412" /><file name="pt-br.js" server="ftp.collegeplacementservices.org" local="3425390845" remote="12018298412" /><file name="pt.js" server="ftp.collegeplacementservices.org" local="3425390845" remote="12018298412" /><file name="ro.js" server="ftp.collegeplacementservices.org" local="3425390845" remote="12018298412" /><file name="ru.js" server="ftp.collegeplacementservices.org" local="3425390845" remote="12018298412" /><file name="sk.js" server="ftp.collegeplacementservices.org" local="3425390845" remote="12018298412" /><file name="sl.js" server="ftp.collegeplacementservices.org" local="3425390845" remote="12018298412" /><file name="sr-latn.js" server="ftp.collegeplacementservices.org" local="3425390845" remote="12018298412" /><file name="sr.js" server="ftp.collegeplacementservices.org" local="3425390845" remote="12018298412" /><file name="sv.js" server="ftp.collegeplacementservices.org" local="3425390845" remote="12018298412" /><file name="th.js" server="ftp.collegeplacementservices.org" local="3425390845" remote="12018298412" /><file name="tr.js" server="ftp.collegeplacementservices.org" local="3425390845" remote="12018298412" /><file name="ug.js" server="ftp.collegeplacementservices.org" local="3425390845" remote="12018298412" /><file name="uk.js" server="ftp.collegeplacementservices.org" local="3425390845" remote="12018298412" /><file name="vi.js" server="ftp.collegeplacementservices.org" local="3425390845" remote="12018298412" /><file name="zh-cn.js" server="ftp.collegeplacementservices.org" local="3425390845" remote="12018298412" /><file name="zh.js" server="ftp.collegeplacementservices.org" local="3425390845" remote="12018298412" /></dwsync>